ssl_metrics_github_issues/__init__.py
ssl_metrics_github_issues/args.py
ssl_metrics_github_issues/bugzilla.py
ssl_metrics_github_issues/github.py
ssl_metrics_github_issues/gitlab.py
ssl_metrics_github_issues/graph.py
ssl_metrics_github_issues/version.py
ssl_metrics_github_issues-0.8.1.dist-info/LICENSE
ssl_metrics_github_issues-0.8.1.dist-info/METADATA
ssl_metrics_github_issues-0.8.1.dist-info/WHEEL
ssl_metrics_github_issues-0.8.1.dist-info/entry_points.txt
ssl_metrics_github_issues-0.8.1.dist-info/top_level.txt
ssl_metrics_github_issues-0.8.1.dist-info/RECORD
