Metadata-Version: 2.1
Name: ssl-metrics-github-issues
Version: 0.8.1
Summary: SSL Metrics - GitHub Issues Analysis
Home-page: https://ssl.cs.luc.edu/projects/metricsDashboard
Author: Software and Systems Laboratory - Loyola University Chicago
Author-email: ssl-metrics@ssl.luc.edu
License: BSD
Project-URL: Bug Tracker, https://github.com/SoftwareSystemsLaboratory/ssl-metrics-github-issues/issues
Project-URL: GitHub Repository, https://github.com/SoftwareSystemsLaboratory/ssl-metrics-github-issues
Keywords: bus factor,commits,engineering,git,github,issue density,issues,kloc,loyola,loyola university chicago,luc,mining,metrics,repository,repository mining,simple,software,software engineering,software metrics,software systems laboratory,ssl
Platform: UNKNOWN
Requires-Python: >=3.9
License-File: LICENSE
Requires-Dist: intervaltree
Requires-Dist: numpy
Requires-Dist: matplotlib
Requires-Dist: pandas
Requires-Dist: progress
Requires-Dist: python-dateutil
Requires-Dist: requests
